<?xml version="1.0" encoding="UTF-8"?>
<objects serializationModel="Studio.02.01.00">
	<object class="ParameterPreset" id="{553d87c3-af55-4f67-ac0b-37a0ccf043ed}">
		<property name="name">
			<value>stairs (on-off)</value>
		</property>
		<relationship name="folder">
			<destination>{c44c88ab-d3b8-4d62-a515-ab3778128c3b}</destination>
		</relationship>
		<relationship name="parameter">
			<destination>{4d7ab21f-6027-45ac-95cb-9a8efa28a1cf}</destination>
		</relationship>
	</object>
	<object class="GameParameter" id="{4d7ab21f-6027-45ac-95cb-9a8efa28a1cf}">
		<property name="parameterType">
			<value>2</value>
		</property>
		<property name="maximum">
			<value>2</value>
		</property>
		<property name="enumerationLabels">
			<value>on</value>
			<value>off</value>
		</property>
		<property name="isGlobal">
			<value>true</value>
		</property>
		<property name="initialValue">
			<value>1</value>
		</property>
		<property name="isExposedRecursively">
			<value>false</value>
		</property>
	</object>
</objects>
